dyncss/__init__.py
dyncss/admin.py
dyncss/apps.py
dyncss/models.py
dyncss/urls.py
dyncss/views.py
dyncss/migrations/0001_initial.py
dyncss/migrations/__init__.py
dyncss/templates/admin/change_form.html
dyncss/templates/admin/file/change_form.html
dyncss/templates/admin/version/change_form.html
dyncss/templatetags/__init__.py
dyncss/templatetags/dyncss.py
django_dyncss-0.1.1.dist-info/COPYING
django_dyncss-0.1.1.dist-info/METADATA
django_dyncss-0.1.1.dist-info/WHEEL
django_dyncss-0.1.1.dist-info/top_level.txt
django_dyncss-0.1.1.dist-info/RECORD
