Metadata-Version: 2.1
Name: django-dyncss
Version: 0.1.1
Summary: django-dyncss is an extension to Django allowing to save css assets in the DB
Home-page: https://github.com/jcolot/django-dyncss
Author: Julien Colot
Author-email: julien.colot@gmail.com
License: MIT
Platform: UNKNOWN
Classifier: Development Status :: 4 - Beta
Classifier: Topic :: Internet :: WWW/HTTP :: Dynamic Content
Classifier: Intended Audience :: Developers
Classifier: Framework :: Django :: 2.2
Classifier: Framework :: Django
Classifier: License :: OSI Approved :: MIT License
Classifier: Programming Language :: Python
Classifier: Topic :: Software Development :: Libraries :: Python Modules
Classifier: Operating System :: OS Independent
Classifier: Programming Language :: Python
Classifier: Programming Language :: Python :: 3
Classifier: Programming Language :: Python :: 3.6
Classifier: Programming Language :: Python :: 3.7
License-File: COPYING
Requires-Dist: django (>=2.23)
Requires-Dist: csscompressor (==0.9.5)
